{
    "parameters": {
        "env": "%general.env%"
    },

    "services": [
        {
            "id": "wx.configuration",
            "class": "wx.core.config.Configuration"
        },
        {
            "id": "wx.routing",
            "class": "wx.core.routing.Routing",
            "parameters": [
                "@wx.context@"
            ]
        },
        {
            "id": "wx.resolver",
            "class": "wx.core.controller.Resolver"
        },
        {
            "id": "wx.context",
            "class": "wx.core.context.Context",
            "parameters": [
                "%env%"
            ]
        }
    ]
}